django_request_queue_timeout-1.0.4.dist-info/licenses/LICENSE.txt
rqto/__init__.py
rqto/middleware.py
django_request_queue_timeout-1.0.4.dist-info/METADATA
django_request_queue_timeout-1.0.4.dist-info/WHEEL
django_request_queue_timeout-1.0.4.dist-info/top_level.txt
django_request_queue_timeout-1.0.4.dist-info/RECORD
