Metadata-Version: 2.4
Name: django-request-queue-timeout
Version: 1.0.4
Summary: Django middleware class to quickly dispatch any requests that wait too long in a queue before being processed
License: MIT License
Keywords: django,queue,timeout
License-File: LICENSE.txt
Requires-Dist: django<6,>=4.2
Provides-Extra: dev
Requires-Dist: bandit>=1.7.4; extra == "dev"
Requires-Dist: coverage[toml]==6.3.2; extra == "dev"
Requires-Dist: freezegun~=0.3.15; extra == "dev"
Requires-Dist: ipython~=7.15.0; extra == "dev"
Requires-Dist: ruff~=0.1.2; extra == "dev"
Dynamic: license-file
